{"data": [
	{
		"id": 201,
		"itemTypeName": "Traje Comum"
	},
	{
		"id": 202,
		"itemTypeName": "Traje Excelente"
	},
	{
		"id": 203,
		"itemTypeName": "Traje Raro"
	},
	{
		"id": 204,
		"itemTypeName": "Traje Épico"
	},
	{
		"id": 205,
		"itemTypeName": "Traje Supremo"
	},
	{
		"id": 206,
		"itemTypeName": "Traje Lendário"
	},
	{
		"id": 207,
		"itemTypeName": "Traje Épico S"
	},
	{
		"id": 208,
		"itemTypeName": "Traje Supremo S"
	},
	{
		"id": 209,
		"itemTypeName": "Traje Lendário S"
	}
]}
