{"data": [
	{
		"id": 1001,
		"name": "地精头斧养成包"
	},
	{
		"id": 1002,
		"name": "围巾养成包"
	},
	{
		"id": 1003,
		"name": "雷电法杖养成包"
	},
	{
		"id": 1004,
		"name": "时间沙漏养成包"
	},
	{
		"id": 1005,
		"name": "水晶球养成包"
	},
	{
		"id": 1101,
		"name": "莉莉丝养成包"
	},
	{
		"id": 1102,
		"name": "广告卷礼包"
	},
	{
		"id": 1103,
		"name": "魔杖盒养成包"
	},
	{
		"id": 1104,
		"name": "飞天扫把养成包"
	},
	{
		"id": 1105,
		"name": "皮皮鬼养成包"
	},
	{
		"id": 1106,
		"name": "金沙养成包"
	},
	{
		"id": 1201,
		"name": "英雄养成包"
	},
	{
		"id": 1202,
		"name": "武器养成包"
	},
	{
		"id": 1203,
		"name": "武器招募包"
	},
	{
		"id": 1204,
		"name": "小钥匙礼包"
	},
	{
		"id": 1205,
		"name": "大钥匙礼包"
	},
	{
		"id": 1301,
		"name": "英雄养成包"
	},
	{
		"id": 1302,
		"name": "武器养成包"
	},
	{
		"id": 1303,
		"name": "钥匙礼包"
	},
	{
		"id": 1304,
		"name": "服饰礼包"
	},
	{
		"id": 1305,
		"name": "钥匙礼包"
	},
	{
		"id": 1306,
		"name": "钥匙礼包"
	},
	{
		"id": 1307,
		"name": "钥匙礼包"
	}
]}
