{"data": [
	{
		"id": 1,
		"name": "Battle"
	},
	{
		"id": 2,
		"name": "Patrol"
	},
	{
		"id": 3,
		"name": "Equipment"
	},
	{
		"id": 4,
		"name": "Shop"
	},
	{
		"id": 5,
		"name": "Rankings"
	},
	{
		"id": 6,
		"name": "Infinite Adventure"
	},
	{
		"id": 7,
		"name": "Hero"
	},
	{
		"id": 8,
		"name": "Daily Challenge"
	},
	{
		"id": 9,
		"name": "Sacred Relic"
	},
	{
		"id": 11,
		"name": "Clothing"
	},
	{
		"id": 12,
		"name": "Forest Adventure "
	},
	{
		"id": 13,
		"name": "Shopping Frenzy"
	},
	{
		"id": 101,
		"name": "Monthly Pass"
	},
	{
		"id": 102,
		"name": "Chapter Package"
	},
	{
		"id": 103,
		"name": "Daily Shop"
	},
	{
		"id": 104,
		"name": "Beginner Package"
	},
	{
		"id": 105,
		"name": "Special Pass"
	},
	{
		"id": 106,
		"name": "每日特惠礼包"
	},
	{
		"id": 107,
		"name": "Special Shop"
	},
	{
		"id": 108,
		"name": "Lucky Wheel"
	},
	{
		"id": 109,
		"name": "Diamond Pass"
	},
	{
		"id": 110,
		"name": "Wish"
	},
	{
		"id": 111,
		"name": "Magic Wish"
	},
	{
		"id": 112,
		"name": "Magic Academy"
	},
	{
		"id": 113,
		"name": "Lucky Journey"
	},
	{
		"id": 114,
		"name": "Magic Era"
	},
	{
		"id": 115,
		"name": "Lucky Gashapon"
	},
	{
		"id": 116,
		"name": "Autumn Special Offer"
	},
	{
		"id": 117,
		"name": "Magic Bingo"
	},
	{
		"id": 664,
		"name": "邀请好友"
	},
	{
		"id": 665,
		"name": "引导好评"
	},
	{
		"id": 666,
		"name": "Redemption Code"
	}
]}
